README.rst
setup.py
django_cuelogic_comments/Comments.py
django_cuelogic_comments/__init__.py
django_cuelogic_comments/admin.py
django_cuelogic_comments/forms.py
django_cuelogic_comments/models.py
django_cuelogic_comments.egg-info/PKG-INFO
django_cuelogic_comments.egg-info/SOURCES.txt
django_cuelogic_comments.egg-info/dependency_links.txt
django_cuelogic_comments.egg-info/pbr.json
django_cuelogic_comments.egg-info/top_level.txt
django_cuelogic_comments/docs/__init__.py
django_cuelogic_comments/static/__init__.py
django_cuelogic_comments/static/style.css
django_cuelogic_comments/templates/__init__.py
django_cuelogic_comments/templates/comments/__init__.py
django_cuelogic_comments/templates/comments/index.html