Metadata-Version: 1.1
Name: django-cuelogic-comments
Version: 0.1
Summary: A simple Django app for manage comments.
Home-page: #
Author: Dadaso Zanzane
Author-email: dadaso.zanzane@cuelogic.co.in
License: BSD License
Platform: UNKNOWN
Classifier: Environment :: Web Environment
Classifier: Framework :: Django
Classifier: Intended Audience :: Developers
Classifier: License :: OSI Approved :: BSD License
Classifier: Operating System :: OS Independent
Classifier: Programming Language :: Python
Classifier: Programming Language :: Python :: 2.7
Classifier: Programming Language :: Python :: 3
Classifier: Topic :: Internet :: WWW/HTTP
Classifier: Topic :: Internet :: WWW/HTTP :: Dynamic Content
